LICENSE.md
MANIFEST.in
README.md
pyproject.toml
readme.txt
setup.py
src/psk_viewer/__init__.py
src/psk_viewer/__main__.py
src/psk_viewer/_version.py
src/psk_viewer/app.py
src/psk_viewer/averaged fs signal filtered.csv
src/psk_viewer/colorselector.py
src/psk_viewer/data_model.py
src/psk_viewer/detection.py
src/psk_viewer/file_dialog.py
src/psk_viewer/found_lines_model.py
src/psk_viewer/gui.py
src/psk_viewer/open_file_path_entry.py
src/psk_viewer/plot_data_item.py
src/psk_viewer/preferences.py
src/psk_viewer/settings.py
src/psk_viewer/table_view.py
src/psk_viewer/toolbar.py
src/psk_viewer/utils.py
src/psk_viewer/valuelabel.py
src/psk_viewer.egg-info/PKG-INFO
src/psk_viewer.egg-info/SOURCES.txt
src/psk_viewer.egg-info/dependency_links.txt
src/psk_viewer.egg-info/entry_points.txt
src/psk_viewer.egg-info/requires.txt
src/psk_viewer.egg-info/top_level.txt
src/psk_viewer/img/main.ico
src/psk_viewer/img/main.svg
src/psk_viewer/translations/ru.qm
src/psk_viewer/translations/ru.ts