Metadata-Version: 2.4
Name: psk_viewer
Version: 0.10.0
Summary: IPM RAS PSK and FS spectrometer files viewer
Author-email: StSav012 <stsav012@gmail.com>
License-Expression: LGPL-3.0-only
Project-URL: Source Code, https://github.com/StSav012/psk_viewer
Project-URL: Bug Tracker, https://github.com/StSav012/psk_viewer/issues
Classifier: Development Status :: 4 - Beta
Classifier: Environment :: Win32 (MS Windows)
Classifier: Environment :: X11 Applications :: Qt
Classifier: Intended Audience :: Science/Research
Classifier: Operating System :: Microsoft :: Windows
Classifier: Operating System :: POSIX
Classifier: Programming Language :: Python :: 3
Classifier: Topic :: Scientific/Engineering
Classifier: Topic :: Scientific/Engineering :: Astronomy
Classifier: Topic :: Scientific/Engineering :: Atmospheric Science
Classifier: Topic :: Scientific/Engineering :: Chemistry
Classifier: Topic :: Scientific/Engineering :: Physics
Classifier: Typing :: Typed
Requires-Python: >=3.9
License-File: LICENSE.md
Requires-Dist: qtpy>=2.4.1
Requires-Dist: qtawesome
Requires-Dist: PySide6-Essentials!=6.8.0,!=6.8.0.1,!=6.9.1,>=6.6.2
Requires-Dist: pandas
Requires-Dist: pyqtgraph>=0.13.3
Requires-Dist: scipy
Dynamic: license-file
Dynamic: requires-dist
